odoo/addons/beesdoo_pos/README.rst
odoo/addons/beesdoo_pos/__init__.py
odoo/addons/beesdoo_pos/__manifest__.py
odoo/addons/beesdoo_pos/i18n/beesdoo_pos.pot
odoo/addons/beesdoo_pos/readme/CONTRIBUTORS.rst
odoo/addons/beesdoo_pos/readme/DESCRIPTION.rst
odoo/addons/beesdoo_pos/static/description/index.html
odoo12_addon_beesdoo_pos-12.0.3.0.0.dist-info/METADATA
odoo12_addon_beesdoo_pos-12.0.3.0.0.dist-info/WHEEL
odoo12_addon_beesdoo_pos-12.0.3.0.0.dist-info/top_level.txt
odoo12_addon_beesdoo_pos-12.0.3.0.0.dist-info/RECORD
