Metadata-Version: 2.1
Name: odoo12-addon-beesdoo-pos
Version: 12.0.3.0.0
Summary: Emptied.
Home-page: https://github.com/beescoop/Obeesdoo
Author: BEES coop - Cellule IT, Coop IT Easy SC
License: AGPL-3
Platform: UNKNOWN
Classifier: Programming Language :: Python
Classifier: Framework :: Odoo
Classifier: Framework :: Odoo :: 12.0
Classifier: License :: OSI Approved :: GNU Affero General Public License v3
Requires-Python: >=3.5
Requires-Dist: odoo12-addon-pos-auto-invoice-company
Requires-Dist: odoo12-addon-pos-available-in-pos-unlink
Requires-Dist: odoo12-addon-pos-eater
Requires-Dist: odoo12-addon-pos-hide-partner-info
Requires-Dist: odoo12-addon-pos-partner-no-create
Requires-Dist: odoo (<12.1dev,>=12.0a)
